spotify_models/__init__.py
spotify_models/models.py
spotify_models-0.0.1.dist-info/LICENSE
spotify_models-0.0.1.dist-info/METADATA
spotify_models-0.0.1.dist-info/WHEEL
spotify_models-0.0.1.dist-info/top_level.txt
spotify_models-0.0.1.dist-info/RECORD
